{"wonders_of_the_world":{"name":"Wonders of the World","icon":"https://static.wikia.nocookie.net/gensin-impact/images/1/17/Achievement_Wonders_of_the_World.png","version":"1.0","namecard":"none","rewards":2850,"achievements":477},"memories_of_the_heart":{"name":"Memories of the Heart","icon":"https://static.wikia.nocookie.net/gensin-impact/images/8/8d/Achievement_Memories_of_the_Heart.png","version":"1.5","namecard":"none","rewards":510,"achievements":51},"mortal_travails_series_i":{"name":"Mortal Travails: Series I","icon":"https://static.wikia.nocookie.net/gensin-impact/images/4/4d/Achievement_Mortal_Travails_Series_I.png","version":"1.0","namecard":"achievement_explorer","rewards":30,"achievements":6},"mortal_travails_series_ii":{"name":"Mortal Travails: Series II","icon":"https://static.wikia.nocookie.net/gensin-impact/images/4/40/Achievement_Mortal_Travails_Series_II.png","version":"2.0","namecard":"achievement_traversal","rewards":25,"achievements":5},"mortal_travails_series_iii":{"name":"Mortal Travails: Series III","icon":"https://static.wikia.nocookie.net/gensin-impact/images/0/07/Achievement_Mortal_Travails_Series_III.png","version":"3.0","namecard":"achievement_roaming","rewards":20,"achievements":4},"the_art_of_adventure":{"name":"The Art of Adventure","icon":"https://static.wikia.nocookie.net/gensin-impact/images/b/b8/Achievement_The_Art_of_Adventure.png","version":"1.0","namecard":"achievement_virtuoso","rewards":80,"achievements":3},"the_heros_journey":{"name":"The Hero's Journey","icon":"https://static.wikia.nocookie.net/gensin-impact/images/a/a7/Achievement_The_Hero%27s_Journey.png","version":"1.0","namecard":"achievement_hero","rewards":170,"achievements":8},"mondstadt_the_city_of_wind_and_song":{"name":"Mondstadt: The City of Wind and Song","icon":"https://static.wikia.nocookie.net/gensin-impact/images/d/df/Achievement_Mondstadt_The_City_of_Wind_and_Song.png","version":"1.0","namecard":"mondstadt_whistling_wind","rewards":145,"achievements":7},"liyue_the_harbor_of_stone_and_contracts":{"name":"Liyue: The Harbor of Stone and Contracts","icon":"https://static.wikia.nocookie.net/gensin-impact/images/3/30/Achievement_Liyue_The_Harbor_of_Stone_and_Contracts.png","version":"1.0","namecard":"liyue_stillness_of_stone","rewards":145,"achievements":7},"elemental_specialist_series_i":{"name":"Elemental Specialist: Series I","icon":"https://static.wikia.nocookie.net/gensin-impact/images/1/1a/Achievement_Elemental_Specialist_Series_I.png","version":"1.0","namecard":"achievement_colors_of_the_rainbow","rewards":245,"achievements":7},"elemental_specialist_series_ii":{"name":"Elemental Specialist: Series II","icon":"https://static.wikia.nocookie.net/gensin-impact/images/f/f6/Achievement_Elemental_Specialist_Series_II.png","version":"3.1","namecard":"achievement_seven_lights","rewards":75,"achievements":3},"marksmanship":{"name":"Marksmanship","icon":"https://static.wikia.nocookie.net/gensin-impact/images/b/b3/Achievement_Marksmanship.png","version":"1.0","namecard":"achievement_bowmaster","rewards":15,"achievements":3},"challenger_series_i":{"name":"Challenger: Series I","icon":"https://static.wikia.nocookie.net/gensin-impact/images/7/75/Achievement_Challenger_Series_I.png","version":"1.0","namecard":"achievement_challenger","rewards":20,"achievements":4},"challenger_series_ii":{"name":"Challenger: Series II","icon":"https://static.wikia.nocookie.net/gensin-impact/images/2/26/Achievement_Challenger_Series_II.png","version":"1.1","namecard":"achievement_challenger_ii","rewards":85,"achievements":8},"challenger_series_iii":{"name":"Challenger: Series III","icon":"https://static.wikia.nocookie.net/gensin-impact/images/d/d7/Achievement_Challenger_Series_III.png","version":"1.2","namecard":"achievement_challenger_iii","rewards":50,"achievements":8},"challenger_series_iv":{"name":"Challenger: Series IV","icon":"https://static.wikia.nocookie.net/gensin-impact/images/f/f8/Achievement_Challenger_Series_IV.png","version":"2.0","namecard":"achievement_stone_dragon","rewards":55,"achievements":9},"challenger_series_v":{"name":"Challenger: Series V","icon":"https://static.wikia.nocookie.net/gensin-impact/images/c/cb/Achievement_Challenger_Series_V.png","version":"2.6","namecard":"achievement_thunderclap","rewards":50,"achievements":8},"challenger_series_vi":{"name":"Challenger: Series VI","icon":"https://static.wikia.nocookie.net/gensin-impact/images/0/03/Achievement_Challenger_Series_VI.png","version":"3.1","namecard":"achievement_mirrored_dreams","rewards":40,"achievements":8},"challenger_series_vii":{"name":"Challenger: Series VII","icon":"https://static.wikia.nocookie.net/gensin-impact/images/4/44/Achievement_Challenger_Series_VII.png","version":"3.6","namecard":"achievement_transient_twilight","rewards":55,"achievements":8},"domains_and_spiral_abyss_series_i":{"name":"Domains and Spiral Abyss: Series I","icon":"https://static.wikia.nocookie.net/gensin-impact/images/7/79/Achievement_Domains_and_Spiral_Abyss_Series_I.png","version":"1.0","namecard":"achievement_deep_dark","rewards":100,"achievements":4},"olah_series_i":{"name":"Olah!: Series I","icon":"https://static.wikia.nocookie.net/gensin-impact/images/4/4a/Achievement_Olah%21_Series_I.png","version":"1.0","namecard":"achievement_hill_dwellers","rewards":10,"achievements":2},"snezhnaya_does_not_believe_in_tears_series_i":{"name":"Snezhnaya Does Not Believe in Tears: Series I","icon":"https://static.wikia.nocookie.net/gensin-impact/images/2/2f/Achievement_Snezhnaya_Does_Not_Believe_in_Tears_Series_I.png","version":"1.0","namecard":"achievement_snowy_land","rewards":10,"achievements":2},"stone_harbors_nostalgia_series_i":{"name":"Stone Harbor's Nostalgia: Series I","icon":"https://static.wikia.nocookie.net/gensin-impact/images/3/3c/Achievement_Stone_Harbor%27s_Nostalgia_Series_I.png","version":"1.0","namecard":"achievement_cliffhanger","rewards":15,"achievements":3},"meetings_in_outrealm_series_i":{"name":"Meetings in Outrealm: Series I","icon":"https://static.wikia.nocookie.net/gensin-impact/images/0/00/Achievement_Meetings_in_Outrealm_Series_I.png","version":"1.0","namecard":"achievement_reunion","rewards":140,"achievements":9},"meetings_in_outrealm_series_ii":{"name":"Meetings in Outrealm: Series II","icon":"https://static.wikia.nocookie.net/gensin-impact/images/0/0e/Achievement_Meetings_in_Outrealm_Series_II.png","version":"2.0","namecard":"achievement_gate","rewards":70,"achievements":7},"meetings_in_outrealm_series_iii":{"name":"Meetings in Outrealm: Series III","icon":"https://static.wikia.nocookie.net/gensin-impact/images/b/b8/Achievement_Meetings_in_Outrealm_Series_III.png","version":"3.0","namecard":"achievement_fated_encounter","rewards":80,"achievements":8},"visitors_on_the_icy_mountain":{"name":"Visitors on the Icy Mountain","icon":"https://static.wikia.nocookie.net/gensin-impact/images/7/7e/Achievement_Visitors_on_the_Icy_Mountain.png","version":"1.2","namecard":"achievement_snowy_summit","rewards":135,"achievements":7},"a_realm_beyond_series_i":{"name":"A Realm Beyond: Series I","icon":"https://static.wikia.nocookie.net/gensin-impact/images/4/48/Achievement_A_Realm_Beyond_Series_I.png","version":"1.5","namecard":"achievement_tea_time","rewards":285,"achievements":9},"a_realm_beyond_series_ii":{"name":"A Realm Beyond: Series II","icon":"https://static.wikia.nocookie.net/gensin-impact/images/c/c3/Achievement_A_Realm_Beyond_Series_II.png","version":"1.6","namecard":"achievement_vacation_home","rewards":75,"achievements":3},"a_realm_beyond_series_iii":{"name":"A Realm Beyond: Series III","icon":"https://static.wikia.nocookie.net/gensin-impact/images/e/ec/Achievement_A_Realm_Beyond_Series_III.png","version":"2.0","namecard":"achievement_full_bloom","rewards":110,"achievements":4},"inazuma_the_islands_of_thunder_and_eternity_series_i":{"name":"Inazuma: The Islands of Thunder and Eternity - Series I","icon":"https://static.wikia.nocookie.net/gensin-impact/images/5/51/Achievement_Inazuma_-_The_Islands_of_Thunder_and_Eternity_-_Series_I.png","version":"2.0","namecard":"inazuma_kujou_insignia","rewards":230,"achievements":12},"inazuma_the_islands_of_thunder_and_eternity_series_ii":{"name":"Inazuma: The Islands of Thunder and Eternity - Series II","icon":"https://static.wikia.nocookie.net/gensin-impact/images/8/82/Achievement_Inazuma_-_The_Islands_of_Thunder_and_Eternity_-_Series_II.png","version":"2.1","namecard":"inazuma_sangonomiya_crest","rewards":150,"achievements":9},"the_chronicles_of_the_sea_of_fog":{"name":"The Chronicles of the Sea of Fog","icon":"https://static.wikia.nocookie.net/gensin-impact/images/8/84/Achievement_The_Chronicles_of_the_Sea_of_Fog.png","version":"2.2","namecard":"inazuma_eagleplume","rewards":110,"achievements":8},"teyvat_fishing_guide_series_i":{"name":"Teyvat Fishing Guide: Series I","icon":"https://static.wikia.nocookie.net/gensin-impact/images/9/9e/Achievement_Teyvat_Fishing_Guide_-_Series_I.png","version":"2.1","namecard":"achievement_nails","rewards":95,"achievements":10},"the_light_of_day":{"name":"The Light of Day","icon":"https://static.wikia.nocookie.net/gensin-impact/images/a/ae/Achievement_The_Light_of_Day.png","version":"2.4","namecard":"inazuma_tokoyo","rewards":125,"achievements":6},"chasmlighter":{"name":"Chasmlighter","icon":"https://static.wikia.nocookie.net/gensin-impact/images/b/be/Achievement_Chasmlighter.png","version":"2.6","namecard":"achievement_chasm","rewards":160,"achievements":9},"sumeru_the_rainforest_of_lore":{"name":"Sumeru: The Rainforest of Lore","icon":"https://static.wikia.nocookie.net/gensin-impact/images/c/c0/Achievement_Sumeru_The_Rainforest_of_Lore.png","version":"3.0","namecard":"sumeru_shimmering_woods","rewards":175,"achievements":9},"sumeru_the_gilded_desert_series_i":{"name":"Sumeru: The Gilded Desert - Series I","icon":"https://static.wikia.nocookie.net/gensin-impact/images/4/4d/Achievement_Sumeru_The_Gilded_Desert_Series_I.png","version":"3.1","namecard":"sumeru_sandtreader","rewards":135,"achievements":7},"sumeru_the_gilded_desert_series_ii":{"name":"Sumeru: The Gilded Desert - Series II","icon":"https://static.wikia.nocookie.net/gensin-impact/images/f/ff/Achievement_Sumeru_The_Gilded_Desert_-_Series_II.png","version":"3.4","namecard":"sumeru_sandstorm","rewards":135,"achievements":7},"genius_invokation_tcg":{"name":"Genius Invokation TCG","icon":"https://static.wikia.nocookie.net/gensin-impact/images/a/a2/Achievement_Genius_Invokation_TCG.png","version":"3.3","namecard":"achievement_invoker","rewards":295,"achievements":10},"blessed_hamada":{"name":"Blessed Hamada","icon":"https://static.wikia.nocookie.net/gensin-impact/images/d/da/Achievement_Blessed_Hamada.png","version":"3.6","namecard":"achievement_infinitum","rewards":155,"achievements":8}}